mcp_ambari_api/__init__.py
mcp_ambari_api/ambari_api.py
mcp_ambari_api/functions.py
mcp_ambari_api/prompt_template.md
mcp_ambari_api-2025.8.12.18.12.53.dist-info/licenses/LICENSE
mcp_ambari_api-2025.8.12.18.12.53.dist-info/METADATA
mcp_ambari_api-2025.8.12.18.12.53.dist-info/WHEEL
mcp_ambari_api-2025.8.12.18.12.53.dist-info/entry_points.txt
mcp_ambari_api-2025.8.12.18.12.53.dist-info/top_level.txt
mcp_ambari_api-2025.8.12.18.12.53.dist-info/RECORD
