Metadata-Version: 2.4
Name: mcp-ambari-api
Version: 2025.8.12.18.12.53
Summary: Model Context Protocol (MCP) server for Apache Ambari API integration. Provides comprehensive tools for managing Hadoop clusters including service operations, configuration management, status monitoring, and request tracking.
Requires-Python: >=3.11
License-File: LICENSE
Requires-Dist: aiohttp>=3.12.15
Requires-Dist: fastmcp>=2.11.1
Provides-Extra: dev
Requires-Dist: pytest>=8.2.0; extra == "dev"
Dynamic: license-file
